elflookup.cpython-310-x86_64-linux-gnu.so
pyelfdata.py
elflookup-0.1.2.dist-info/LICENSE
elflookup-0.1.2.dist-info/WHEEL
elflookup-0.1.2.dist-info/RECORD
elflookup-0.1.2.dist-info/top_level.txt
elflookup-0.1.2.dist-info/METADATA
