Metadata-Version: 2.2
Name: elflookup
Version: 0.1.2
Summary: Simple utility to make it easy to extract data sections from ELF binaries.
Home-page: https://github.com/goodtune/elfdata
Author: Gary Reynolds
Author-email: gary.reynolds@touchtechnology.com.au
Requires-Python: >=3.7
License-File: LICENSE
Dynamic: author
Dynamic: author-email
Dynamic: home-page
Dynamic: requires-python
